app/__init__.py
app/main.py
app/models.py
calculadora_lib/__init__.py
calculadora_lib/operations.py
tests/__init__.py
tests/test_main.py
calculator_lib-0.1.0.dist-info/METADATA
calculator_lib-0.1.0.dist-info/WHEEL
calculator_lib-0.1.0.dist-info/top_level.txt
calculator_lib-0.1.0.dist-info/RECORD
